pdupes/__init__.py
pdupes/cli.py
pdupes/duplicatefinder.py
pdupes-0.0.0.dist-info/DESCRIPTION.rst
pdupes-0.0.0.dist-info/LICENSE.txt
pdupes-0.0.0.dist-info/METADATA
pdupes-0.0.0.dist-info/RECORD
pdupes-0.0.0.dist-info/WHEEL
pdupes-0.0.0.dist-info/entry_points.txt
pdupes-0.0.0.dist-info/metadata.json
pdupes-0.0.0.dist-info/top_level.txt
