Metadata-Version: 2.0
Name: pdupes
Version: 0.0.0
Summary: Python duplicate file checker
Home-page: https://github.com/n8henrie/pdupes
Author: Nathan Henrie
Author-email: nate@n8henrie.com
License: MIT
Keywords: pdupes
Platform: UNKNOWN
Classifier: Natural Language :: English
Classifier: Programming Language :: Python :: 3
Classifier: Programming Language :: Python :: 3.6
Provides-Extra: dev
Requires-Dist: CommonMark (==0.5.5); extra == 'dev'
Requires-Dist: Sphinx (==1.4.9); extra == 'dev'
Requires-Dist: docutils (==0.12); extra == 'dev'
Requires-Dist: flake8 (==3.3.0); extra == 'dev'
Requires-Dist: flake8-docstrings (==1.1.0); extra == 'dev'
Requires-Dist: flake8-import-order (==0.12); extra == 'dev'
Requires-Dist: mypy (==0.501); extra == 'dev'
Requires-Dist: pep8-naming (==0.4.1); extra == 'dev'
Requires-Dist: pylint (==1.7.1); extra == 'dev'
Requires-Dist: pypandoc (==1.3.3); extra == 'dev'
Requires-Dist: pytest (==3.0.4); extra == 'dev'
Requires-Dist: recommonmark (==0.4.0); extra == 'dev'
Requires-Dist: sphinx-rtd-theme (==0.1.9); extra == 'dev'
Requires-Dist: tox (==2.6.0); extra == 'dev'
Requires-Dist: twine (==1.8.1); extra == 'dev'
